WinToastCreator/creator.py
WinToastCreator/utils.py
wintoastcreator-0.4.0.dist-info/licenses/LICENSE
wintoastcreator-0.4.0.dist-info/METADATA
wintoastcreator-0.4.0.dist-info/WHEEL
wintoastcreator-0.4.0.dist-info/top_level.txt
wintoastcreator-0.4.0.dist-info/RECORD
