Metadata-Version: 2.4
Name: WinToastCreator
Version: 0.4.0
Summary: WinToastCreator — модуль для отправки уведомлений в Windows
Author-email: Timofey <timofey1166@gmail.com>
License-Expression: MIT
Keywords: windows,notifications,toast,system-notifications
Classifier: Development Status :: 5 - Production/Stable
Classifier: Intended Audience :: Developers
Classifier: Programming Language :: Python :: 3
Classifier: Programming Language :: Python :: 3.6
Classifier: Programming Language :: Python :: 3.7
Classifier: Programming Language :: Python :: 3.8
Classifier: Programming Language :: Python :: 3.9
Classifier: Programming Language :: Python :: 3.10
Classifier: Programming Language :: Python :: 3.11
Classifier: Programming Language :: Python :: 3.12
Classifier: Programming Language :: Python :: 3.13
Classifier: Programming Language :: Python :: 3.14
Classifier: Operating System :: OS Independent
Requires-Python: >=3.6
License-File: LICENSE
Requires-Dist: winrt-runtime
Requires-Dist: winrt-Windows.Data.Xml.Dom
Requires-Dist: winrt-Windows.Foundation
Requires-Dist: winrt-Windows.Foundation.Collections
Requires-Dist: winrt-Windows.Globalization
Requires-Dist: winrt-Windows.Graphics.Imaging
Requires-Dist: winrt-Windows.Media
Requires-Dist: winrt-Windows.Media.Core
Requires-Dist: winrt-Windows.Media.Ocr
Requires-Dist: winrt-Windows.Media.Playback
Requires-Dist: winrt-Windows.Media.SpeechSynthesis
Requires-Dist: winrt-Windows.Storage
Requires-Dist: winrt-Windows.Storage.Streams
Requires-Dist: winrt-Windows.UI.Notifications
Dynamic: license-file
